<?xml version="1.0" encoding="UTF-8" standalone="yes"?>
<nodes>
    <node>
        <messageType>text</messageType>
        <code>endNode</code>
        <messages>
            <message>
                <value>Commerce</value>
            </message>
        </messages>
    </node>
    <node>
        <messageType>text</messageType>
        <code>successNode</code>
        <messages>
            <message>
                <value>Success</value>
            </message>
        </messages>
    </node>
    <node>
        <messageType>image</messageType>
        <code>startNode</code>
        <messages>
            <message>
                <value>start_01</value>
            </message>
            <message>
                <value>start_02</value>
            </message>
        </messages>
        <image>https://cdn.pixabay.com/photo/2014/04/02/10/47/computer-304585_960_720.png</image>
        <variants>
            <variant>
                <value>yes</value>
                <target>node01</target>
            </variant>
            <variant>
                <value>no</value>
                <target>node02</target>
            </variant>
            <variant>
                <value>I_dont_know</value>
                <target>endNode</target>
            </variant>
        </variants>
    </node>
    <node>
        <messageType>text</messageType>
        <code>node01</code>
        <messages>
            <message>
                <value>Monitor_01</value>
            </message>
        </messages>
        <variants>
            <variant>
                <value>yes</value>
                <target>endNode</target>
            </variant>
            <variant>
                <value>no</value>
                <target>node06</target>
            </variant>
            <variant>
                <value>I_dont_know</value>
                <target>endNode</target>
            </variant>
        </variants>
    </node>
    <node>
        <messageType>text</messageType>
        <code>node02</code>
        <messages>
            <message>
                <value>Monitor_02</value>
            </message>
        </messages>
        <variants>
            <variant>
                <value>yes</value>
                <target>node03</target>
            </variant>
            <variant>
                <value>no</value>
                <target>node04</target>
            </variant>
            <variant>
                <value>I_dont_know</value>
                <target>endNode</target>
            </variant>
        </variants>
    </node>
    <node>
        <messageType>text</messageType>
        <code>node03</code>
        <messages>
            <message>
                <value>Power_01</value>
            </message>
        </messages>
        <variants>
            <variant>
                <value>yes</value>
                <target>node05</target>
            </variant>
            <variant>
                <value>no</value>
                <target>endNode</target>
            </variant>
            <variant>
                <value>I_dont_know</value>
                <target>endNode</target>
            </variant>
        </variants>
    </node>
    <node>
        <messageType>text</messageType>
        <code>node04</code>
        <messages>
            <message>
                <value>Power_02</value>
            </message>
            <message>
                <value>isItWork</value>
            </message>
        </messages>
        <variants>
            <variant>
                <value>yes</value>
                <target>successNode</target>
            </variant>
            <variant>
                <value>no</value>
                <target>endNode</target>
            </variant>
            <variant>
                <value>I_dont_know</value>
                <target>endNode</target>
            </variant>
        </variants>
    </node>
    <node>
        <messageType>text</messageType>
        <code>node05</code>
        <messages>
            <message>
                <value>Power_03</value>
            </message>
            <message>
                <value>isItWork</value>
            </message>
        </messages>
        <variants>
            <variant>
                <value>yes</value>
                <target>successNode</target>
            </variant>
            <variant>
                <value>no</value>
                <target>endNode</target>
            </variant>
            <variant>
                <value>I_dont_know</value>
                <target>endNode</target>
            </variant>
        </variants>
    </node>
    <node>
        <messageType>text</messageType>
        <code>node06</code>
        <messages>
            <message>
                <value>Monitor_03</value>
            </message>
        </messages>
        <variants>
            <variant>
                <value>yes</value>
                <target>endNode</target>
            </variant>
            <variant>
                <value>no</value>
                <target>endNode</target>
            </variant>
            <variant>
                <value>I_dont_know</value>
                <target>endNode</target>
            </variant>
        </variants>
    </node>
    <node>
        <messageType>text</messageType>
        <code>node07</code>
        <type>end</type>
        <nextNode>endNode</nextNode>
        <messages>
            <message>
                <value>Monitor_04</value>
            </message>
            <message>
                <value>isItWork</value>
            </message>
        </messages>
    </node>
</nodes>
